saneyaml.py
saneyaml-0.6.1.dist-info/AUTHORS.rst
saneyaml-0.6.1.dist-info/CHANGELOG.rst
saneyaml-0.6.1.dist-info/CODE_OF_CONDUCT.rst
saneyaml-0.6.1.dist-info/METADATA
saneyaml-0.6.1.dist-info/NOTICE
saneyaml-0.6.1.dist-info/WHEEL
saneyaml-0.6.1.dist-info/apache-2.0.LICENSE
saneyaml-0.6.1.dist-info/top_level.txt
saneyaml-0.6.1.dist-info/RECORD
