Metadata-Version: 2.1
Name: saneyaml
Version: 0.6.1
Summary: Read and write readable YAML safely preserving order and avoiding bad surprises with unwanted infered type conversions. This library is a PyYaml wrapper with sane behaviour to read and write readable YAML safely, typically when used for configuration.
Home-page: https://github.com/aboutcode-org/saneyaml
Author: nexB. Inc. and others
Author-email: info@aboutcode.org
License: Apache-2.0
Keywords: utilities,yaml,pyyaml,block,flow
Classifier: Development Status :: 5 - Production/Stable
Classifier: Intended Audience :: Developers
Classifier: Programming Language :: Python :: 3
Classifier: Programming Language :: Python :: 3 :: Only
Classifier: Topic :: Software Development
Classifier: Topic :: Utilities
Requires-Python: >=3.7
License-File: apache-2.0.LICENSE
License-File: NOTICE
License-File: AUTHORS.rst
License-File: CHANGELOG.rst
License-File: CODE_OF_CONDUCT.rst
Requires-Dist: PyYAML
Provides-Extra: testing
Requires-Dist: pytest!=7.0.0,>=6; extra == "testing"
Requires-Dist: pytest-xdist>=2; extra == "testing"
Requires-Dist: aboutcode-toolkit>=7.0.2; extra == "testing"
Requires-Dist: twine; extra == "testing"
Requires-Dist: black; extra == "testing"
Requires-Dist: isort; extra == "testing"
Provides-Extra: docs
Requires-Dist: Sphinx>=3.3.1; extra == "docs"
Requires-Dist: sphinx-rtd-theme>=0.5.0; extra == "docs"
Requires-Dist: doc8>=0.8.1; extra == "docs"
